django_easy_admin_object_actions/__init__.py
django_easy_admin_object_actions/admin.py
django_easy_admin_object_actions/apps.py
django_easy_admin_object_actions/decorators.py
django_easy_admin_object_actions/templates/easy_admin_object_actions/admin/change_form.html
django_easy_admin_object_actions/templates/easy_admin_object_actions/admin/includes/object_actions_row.html
django_easy_admin_object_actions-1.1.0.dist-info/LICENSE
django_easy_admin_object_actions-1.1.0.dist-info/METADATA
django_easy_admin_object_actions-1.1.0.dist-info/WHEEL
django_easy_admin_object_actions-1.1.0.dist-info/top_level.txt
django_easy_admin_object_actions-1.1.0.dist-info/RECORD
