Metadata-Version: 2.1
Name: django-easy-admin-object-actions
Version: 1.1.0
Summary: Django app to easily add actions to an object's admin change form
Author-email: Job Doesburg <job.doesburg@gmail.com>
License: MIT License        
Project-URL: homepage, https://github.com/JobDoesburg/django-easy-admin-object-actions
Project-URL: repository, https://github.com/JobDoesburg/django-easy-admin-object-actions
Project-URL: documentation, https://github.com/JobDoesburg/django-easy-admin-object-actions
Classifier: License :: OSI Approved :: MIT License
Classifier: Programming Language :: Python
Classifier: Programming Language :: Python :: 3
Classifier: Framework :: Django
Classifier: Framework :: Django :: 3.0
Classifier: Framework :: Django :: 3.1
Classifier: Framework :: Django :: 3.2
Classifier: Framework :: Django :: 4.0
Classifier: Framework :: Django :: 4.1
Classifier: Intended Audience :: Developers
Classifier: Operating System :: OS Independent
Requires-Python: >=3
License-File: LICENSE
Requires-Dist: django (>=3)
